README.txt
setup.cfg
setup.py
obnpy/Callback.py
obnpy/__init__.py
obnpy/obnextapi.py
obnpy/obnnode.py
obnpy/obnport.py
obnpy/simpletest.py
obnpy.egg-info/PKG-INFO
obnpy.egg-info/SOURCES.txt
obnpy.egg-info/dependency_links.txt
obnpy.egg-info/top_level.txt